{
  "file": "/Users/maciek/Desktop/magisterka/MagisterkaProgram/backend_embedded/data/tmp/realtime_candidate/csv/downsampled/udp_sequence/udp_sequence_00002.csv",
  "gender": "female",
  "step_type": "step",
  "fs": 50.0,
  "events": [
    {
      "time": 0.04,
      "label": "L step start"
    },
    {
      "time": 0.16,
      "label": "R step start"
    },
    {
      "time": 0.5,
      "label": "L step end",
      "value": 1.4281139373779297,
      "units": "norm",
      "direction": "forward",
      "max_knee_angle": 60.00733184814453
    },
    {
      "time": 0.92,
      "label": "L step (accented) start"
    },
    {
      "time": 1.16,
      "label": "R step end",
      "value": 1.3825910091400146,
      "units": "norm",
      "direction": "forward",
      "max_knee_angle": 62.69914627075195
    },
    {
      "time": 1.28,
      "label": "R accent start"
    },
    {
      "time": 1.9,
      "label": "L step (accented) end",
      "value": 1.7782530784606934,
      "units": "norm",
      "direction": "forward",
      "max_knee_angle": 76.08737182617188
    },
    {
      "time": 2.08,
      "label": "R accent end",
      "max_knee_angle": 57.07619857788086
    },
    {
      "time": 2.14,
      "label": "R step start"
    },
    {
      "time": 2.2,
      "label": "L step start"
    },
    {
      "time": 2.6,
      "label": "R step end",
      "value": 1.3287440538406372,
      "units": "norm",
      "direction": "forward",
      "max_knee_angle": 62.344478607177734
    },
    {
      "time": 3.26,
      "label": "L step end",
      "value": 1.1951439380645752,
      "units": "norm",
      "direction": "forward",
      "max_knee_angle": 55.75680923461914
    },
    {
      "time": 3.34,
      "label": "R step start"
    },
    {
      "time": 3.96,
      "label": "R step end",
      "value": 1.326332926750183,
      "units": "norm",
      "direction": "forward",
      "max_knee_angle": 79.8949966430664
    }
  ]
}